README.rst
flasfka-serve
setup.py
flasfka/__init__.py
flasfka/api.py
flasfka/tests.py
flasfka.egg-info/PKG-INFO
flasfka.egg-info/SOURCES.txt
flasfka.egg-info/dependency_links.txt
flasfka.egg-info/not-zip-safe
flasfka.egg-info/requires.txt
flasfka.egg-info/top_level.txt