Metadata-Version: 1.1
Name: flasfka
Version: 1.1.5
Summary: 
